{
  "photographer": {
    "name": "Andrés Tuberquia",
    "tagline": "Fotografía de conciertos & retrato",
    "bio": "Cobertura fotográfica de música en vivo y sesiones de retrato en Medellín, Colombia.",
    "instagram": "https://instagram.com/andres_tuberquia_photos",
    "email": "contacto@tudominio.com"
  },
  "sessions": [
    {
      "id": "001",
      "date": "2026-04-01",
      "type": "retrato",
      "title": "Cuerpo",
      "description": "El cuerpo no se rebela: se construye. Fragmentos, repeticiones y silencios definen una presencia que no pide permiso.",
      "credits": [
        { "rol": "Modelo", "nombre": "Mixi Posso" },
        { "rol": "Locación", "nombre": "Bello, Antioquia" }
      ],
      "photos": [
        "https://res.cloudinary.com/dwfrxjqbu/image/upload/v1779858667/0608-01_gc83li.jpg",
        "https://res.cloudinary.com/dwfrxjqbu/image/upload/v1779858667/0599-03_fvfoqn.jpg",
        "https://res.cloudinary.com/dwfrxjqbu/image/upload/v1779858667/0600-02_i9tyfc.jpg",
        "https://res.cloudinary.com/dwfrxjqbu/image/upload/v1779858667/590344-01_maogku.jpg",
        "https://res.cloudinary.com/dwfrxjqbu/image/upload/v1779858666/0603-01_p5t04l.jpg"
      ]
    },
    {
      "id": "002",
      "date": "2025-11-01",
      "type": "concierto",
      "title": "Los Árboles — Altavoz",
      "description": "Cobertura fotográfica de Los Árboles en el festival Altavoz. Energía cruda y luces dramáticas en el Estadio Cincuentenario.",
      "credits": [
        { "rol": "Banda", "nombre": "Los Árboles" },
        { "rol": "Festival", "nombre": "Altavoz" },
        { "rol": "Venue", "nombre": "Estadio Cincuentenario, Medellín" }
      ],
      "photos": [
        "https://res.cloudinary.com/dwfrxjqbu/image/upload/v1779858651/los_arboles_1_rjrdtb.jpg",
        "https://res.cloudinary.com/dwfrxjqbu/image/upload/v1779858655/los_arboles_2_rdiopi.jpg",
        "https://res.cloudinary.com/dwfrxjqbu/image/upload/v1779858651/los_arboles_3_okz2y8.jpg",
        "https://res.cloudinary.com/dwfrxjqbu/image/upload/v1779858651/los_arboles_4_zfz14j.jpg",
        "https://res.cloudinary.com/dwfrxjqbu/image/upload/v1779858651/los_arboles_5_pxsfe8.jpg"
      ]
    }
  ]
}
